pydpm/__init__.py
pydpm/dataloader/__init__.py
pydpm/dataloader/graph_data.py
pydpm/dataloader/image_data.py
pydpm/dataloader/text_data.py
pydpm/example/Sampler_Demo.py
pydpm/example/Sampler_Speed_Demo.py
pydpm/example/__init__.py
pydpm/example/Bayesian_PM/__init__.py
pydpm/example/Bayesian_PM/Convolutional_Poisson_Gamma_Belief_Network/CPFA_Demo.py
pydpm/example/Bayesian_PM/Convolutional_Poisson_Gamma_Belief_Network/CPGBN_Demo.py
pydpm/example/Bayesian_PM/Convolutional_Poisson_Gamma_Belief_Network/__init__.py
pydpm/example/Bayesian_PM/Deep_Poisson_Factor_Analysis/DPFA_Demo.py
pydpm/example/Bayesian_PM/Deep_Poisson_Factor_Analysis/__init__.py
pydpm/example/Bayesian_PM/Deep_Poisson_Gamma_Dynamic_System/DPGDS_Demo.py
pydpm/example/Bayesian_PM/Deep_Poisson_Gamma_Dynamic_System/__init__.py
pydpm/example/Bayesian_PM/Dirchilet_Belief_Network/DirBN_Demo.py
pydpm/example/Bayesian_PM/Dirchilet_Belief_Network/__init__.py
pydpm/example/Bayesian_PM/Factor_Analysis/FA_demo.py
pydpm/example/Bayesian_PM/Factor_Analysis/__init__.py
pydpm/example/Bayesian_PM/Gaussian_Mixture_Model/GMM_Demo.py
pydpm/example/Bayesian_PM/Gaussian_Mixture_Model/__init__.py
pydpm/example/Bayesian_PM/Graph_Poisson_Gamma_Belief_Network/GPGBN_Demo.py
pydpm/example/Bayesian_PM/Graph_Poisson_Gamma_Belief_Network/__init__.py
pydpm/example/Bayesian_PM/Latent_Dirchilet_Allocation/LDA_Demo.py
pydpm/example/Bayesian_PM/Latent_Dirchilet_Allocation/__init__.py
pydpm/example/Bayesian_PM/Multimodal_Poisson_Gamma_Belief_Network/MPGBN_Demo.py
pydpm/example/Bayesian_PM/Multimodal_Poisson_Gamma_Belief_Network/__init__.py
pydpm/example/Bayesian_PM/Poisson_Factor_Analysis/PFA_Demo.py
pydpm/example/Bayesian_PM/Poisson_Factor_Analysis/__init__.py
pydpm/example/Bayesian_PM/Poisson_Gamma_Belief_Network/PGBN_Demo.py
pydpm/example/Bayesian_PM/Poisson_Gamma_Belief_Network/__init__.py
pydpm/example/Bayesian_PM/Poisson_Gamma_Dynamic_System/PGDS_Demo.py
pydpm/example/Bayesian_PM/Poisson_Gamma_Dynamic_System/__init__.py
pydpm-5.1.0.dist-info/LICENSE
pydpm-5.1.0.dist-info/METADATA
pydpm-5.1.0.dist-info/WHEEL
pydpm-5.1.0.dist-info/top_level.txt
pydpm-5.1.0.dist-info/RECORD
