Metadata-Version: 2.1
Name: pydpm
Version: 5.1.0
Summary: A python library focuses on constructing deep probabilistic models on GPU.
Home-page: https://github.com/BoChenGroup/Pydpm
Author: Chaojie Wang, Wei Zhao, Xinyang Liu, Jiawen Wu
Author-email: xd_silly@163.com
Maintainer: BoChenGroup
Maintainer-email: 13279389260@163.com
License: Apache License Version 2.0
Platform: Windows
Platform: Linux
Classifier: Environment :: GPU :: NVIDIA CUDA
Classifier: Intended Audience :: Developers
Classifier: Programming Language :: Python :: 3
Classifier: Topic :: Software Development :: Libraries
Requires: numpy
Requires: scipy
Requires: sklearn
Requires: PyTorch
Requires: ctypes
Requires: subprocess
License-File: LICENSE
